LICENSE
MANIFEST.in
README.md
setup.cfg
setup.py
bin/carbon-aggregator-cache.py
bin/carbon-aggregator.py
bin/carbon-cache.py
bin/carbon-relay.py
bin/validate-storage-schemas.py
conf/aggregation-rules.conf.example
conf/blacklist.conf.example
conf/carbon.amqp.conf.example
conf/carbon.conf.example
conf/relay-rules.conf.example
conf/rewrite-rules.conf.example
conf/storage-aggregation.conf.example
conf/storage-schemas.conf.example
conf/whitelist.conf.example
distro/debian/init.d/carbon-aggregator
distro/debian/init.d/carbon-cache
distro/debian/init.d/carbon-relay
distro/debian/misc/postinstall
distro/redhat/init.d/carbon-aggregator
distro/redhat/init.d/carbon-cache
distro/redhat/init.d/carbon-relay
distro/redhat/misc/postinstall
lib/carbon/__init__.py
lib/carbon/amqp0-8.xml
lib/carbon/amqp_listener.py
lib/carbon/amqp_publisher.py
lib/carbon/cache.py
lib/carbon/carbon_pb2.py
lib/carbon/client.py
lib/carbon/conf.py
lib/carbon/database.py
lib/carbon/events.py
lib/carbon/exceptions.py
lib/carbon/hashing.py
lib/carbon/http.py
lib/carbon/instrumentation.py
lib/carbon/log.py
lib/carbon/management.py
lib/carbon/manhole.py
lib/carbon/pipeline.py
lib/carbon/protobuf.py
lib/carbon/protocols.py
lib/carbon/regexlist.py
lib/carbon/relayrules.py
lib/carbon/resolver.py
lib/carbon/rewrite.py
lib/carbon/routers.py
lib/carbon/service.py
lib/carbon/state.py
lib/carbon/storage.py
lib/carbon/util.py
lib/carbon/writer.py
lib/carbon.egg-info/PKG-INFO
lib/carbon.egg-info/SOURCES.txt
lib/carbon.egg-info/dependency_links.txt
lib/carbon.egg-info/requires.txt
lib/carbon.egg-info/top_level.txt
lib/carbon/aggregator/__init__.py
lib/carbon/aggregator/buffers.py
lib/carbon/aggregator/processor.py
lib/carbon/aggregator/rules.py
lib/twisted/plugins/carbon_aggregator_cache_plugin.py
lib/twisted/plugins/carbon_aggregator_plugin.py
lib/twisted/plugins/carbon_cache_plugin.py
lib/twisted/plugins/carbon_relay_plugin.py